ovos_PHAL_sensors/__init__.py
ovos_PHAL_sensors/__main__.py
ovos_PHAL_sensors/device.py
ovos_PHAL_sensors/version.py
ovos_PHAL_sensors/loggers/__init__.py
ovos_PHAL_sensors/loggers/base.py
ovos_PHAL_sensors/loggers/ha_http.py
ovos_PHAL_sensors/loggers/ha_mqtt.py
ovos_PHAL_sensors/sensors/__init__.py
ovos_PHAL_sensors/sensors/base.py
ovos_PHAL_sensors/sensors/battery.py
ovos_PHAL_sensors/sensors/cpu.py
ovos_PHAL_sensors/sensors/fan.py
ovos_PHAL_sensors/sensors/memory.py
ovos_PHAL_sensors/sensors/network.py
ovos_PHAL_sensors/sensors/os_system.py
ovos_PHAL_sensors/sensors/procs.py
ovos_PHAL_sensors/sensors/extra/__init__.py
ovos_PHAL_sensors/sensors/extra/blue.py
ovos_PHAL_sensors/sensors/extra/pulse.py
ovos_PHAL_sensors/sensors/extra/screen.py
ovos_PHAL_sensors/sensors/extra/wifiscan.py
ovos_PHAL_sensors-0.0.0a17.dist-info/METADATA
ovos_PHAL_sensors-0.0.0a17.dist-info/WHEEL
ovos_PHAL_sensors-0.0.0a17.dist-info/entry_points.txt
ovos_PHAL_sensors-0.0.0a17.dist-info/top_level.txt
ovos_PHAL_sensors-0.0.0a17.dist-info/zip-safe
ovos_PHAL_sensors-0.0.0a17.dist-info/RECORD
