Metadata-Version: 2.1
Name: ovos-PHAL-sensors
Version: 0.0.0a17
Summary: Expose OVOS device sensors to IOT frameworks
Home-page: https://github.com/OpenVoiceOS/ovos-PHAL-sensors
Author: JarbasAi
Author-email: jarbasai@mailfence.com
License: Apache-2.0
Platform: UNKNOWN
Classifier: Development Status :: 3 - Alpha
Classifier: Intended Audience :: Developers
Classifier: Topic :: Text Processing :: Linguistic
Classifier: License :: OSI Approved :: Apache Software License
Classifier: Programming Language :: Python :: 3.5
Classifier: Programming Language :: Python :: 3.6
Requires-Dist: ovos-plugin-manager ~=0.0
Requires-Dist: psutil
Requires-Dist: requests
Requires-Dist: unidecode
